aliyunsdkcassandra/__init__.py
aliyunsdkcassandra/endpoint.py
aliyunsdkcassandra/request/__init__.py
aliyunsdkcassandra/request/v20190101/AllocatePublicContactPointsRequest.py
aliyunsdkcassandra/request/v20190101/CreateBackupPlanRequest.py
aliyunsdkcassandra/request/v20190101/CreateClusterRequest.py
aliyunsdkcassandra/request/v20190101/CreateDataCenterRequest.py
aliyunsdkcassandra/request/v20190101/DeleteBackupPlanRequest.py
aliyunsdkcassandra/request/v20190101/DeleteClusterRequest.py
aliyunsdkcassandra/request/v20190101/DeleteDataCenterRequest.py
aliyunsdkcassandra/request/v20190101/DeleteNodeToolExecutionHistoryRequest.py
aliyunsdkcassandra/request/v20190101/DescribeAccountsRequest.py
aliyunsdkcassandra/request/v20190101/DescribeBackupPlanRequest.py
aliyunsdkcassandra/request/v20190101/DescribeBackupPlansRequest.py
aliyunsdkcassandra/request/v20190101/DescribeBackupRequest.py
aliyunsdkcassandra/request/v20190101/DescribeBackupsRequest.py
aliyunsdkcassandra/request/v20190101/DescribeClusterDashboardRequest.py
aliyunsdkcassandra/request/v20190101/DescribeClusterRequest.py
aliyunsdkcassandra/request/v20190101/DescribeClusterStatusRequest.py
aliyunsdkcassandra/request/v20190101/DescribeClustersRequest.py
aliyunsdkcassandra/request/v20190101/DescribeContactPointsRequest.py
aliyunsdkcassandra/request/v20190101/DescribeDataCenterRequest.py
aliyunsdkcassandra/request/v20190101/DescribeDataCentersRequest.py
aliyunsdkcassandra/request/v20190101/DescribeDeletedClustersRequest.py
aliyunsdkcassandra/request/v20190101/DescribeInstanceTypeRequest.py
aliyunsdkcassandra/request/v20190101/DescribeIpWhitelistGroupsRequest.py
aliyunsdkcassandra/request/v20190101/DescribeIpWhitelistRequest.py
aliyunsdkcassandra/request/v20190101/DescribeNodeToolExecutionHistoriesRequest.py
aliyunsdkcassandra/request/v20190101/DescribeNodeToolExecutionHistoryRequest.py
aliyunsdkcassandra/request/v20190101/DescribeParameterModificationHistoriesRequest.py
aliyun_python_sdk_cassandra-1.0.7.dist-info/LICENSE
aliyun_python_sdk_cassandra-1.0.7.dist-info/METADATA
aliyun_python_sdk_cassandra-1.0.7.dist-info/WHEEL
aliyun_python_sdk_cassandra-1.0.7.dist-info/top_level.txt
aliyun_python_sdk_cassandra-1.0.7.dist-info/RECORD
